manage.py
run.py
apps/__init__.py
apps/calendars/__init__.py
apps/calendars/admin.py
apps/calendars/apps.py
apps/calendars/filters.py
apps/calendars/forms.py
apps/calendars/models.py
apps/calendars/recurrences.py
apps/calendars/urls.py
apps/calendars/views.py
apps/calendars/migrations/0001_initial.py
apps/calendars/migrations/__init__.py
apps/calendars/templatetags/__init__.py
apps/calendars/templatetags/event_color.py
apps/recurrence/__init__.py
apps/recurrence/forms.py
config/__init__.py
config/asgi.py
config/settings.py
config/urls.py
config/wsgi.py
calendar_event_ease-0.1.0.dist-info/METADATA
calendar_event_ease-0.1.0.dist-info/WHEEL
calendar_event_ease-0.1.0.dist-info/entry_points.txt
calendar_event_ease-0.1.0.dist-info/RECORD
