Metadata-Version: 2.1
Name: calendar-event-ease
Version: 0.1.0
Summary: Simpler interface to manage your google calendar events
Author-email: mathiasag7 <mathiasag07@gmail.com>
Requires-Python: >=3.8
Requires-Dist: crispy-bootstrap5>=0.7
Requires-Dist: django
Requires-Dist: django-crispy-forms>=2.1
Requires-Dist: django-htmx>=1.17.0
Requires-Dist: django-recurrence>=1.11.1
Requires-Dist: django-render-block>=0.9.2
Requires-Dist: gcsa>=2.1.0
Requires-Dist: gunicorn>=21.2.0
